ovitoclient/__init__.py
ovitoclient/ovitoclient.py
ovitoclient-0.3.1.data/scripts/ovitoclient
ovitoclient-0.3.1.dist-info/METADATA
ovitoclient-0.3.1.dist-info/RECORD
ovitoclient-0.3.1.dist-info/WHEEL
ovitoclient-0.3.1.dist-info/top_level.txt
