Metadata-Version: 2.1
Name: ovitoclient
Version: 0.3.1
Summary: Ovito Client is a command-line utility with some basic rendering capabilities for trajectory files using Ovito.
Home-page: https://github.com/benlindsay/ovitoclient
Author: Ben Lindsay
Author-email: benjlindsay@gmail.com
License: MIT license
Keywords: ovitoclient
Platform: UNKNOWN
Classifier: Development Status :: 2 - Pre-Alpha
Classifier: Intended Audience :: Developers
Classifier: License :: OSI Approved :: MIT License
Classifier: Natural Language :: English
Classifier: Programming Language :: Python :: 3
Classifier: Programming Language :: Python :: 3.4
Classifier: Programming Language :: Python :: 3.5
Classifier: Programming Language :: Python :: 3.6
Classifier: Programming Language :: Python :: 3.7
